simplebayesuncertainty/__init__.py
simplebayesuncertainty/bayes_uncertainty_util.py
simplebayesuncertainty-0.0.1.dist-info/LICENSE
simplebayesuncertainty-0.0.1.dist-info/METADATA
simplebayesuncertainty-0.0.1.dist-info/WHEEL
simplebayesuncertainty-0.0.1.dist-info/top_level.txt
simplebayesuncertainty-0.0.1.dist-info/RECORD
