Metadata-Version: 2.1
Name: simplebayesuncertainty
Version: 0.0.1
Summary: The paper provides a simple and easy method to employ the Bayesian paradigm for typical applications in metrology.  The suggested choice for the prior, the sampling methods and the analysis of the resulting posterior is covered in this repository.
Home-page: https://github.com/manuelmarschall/SimpleBayesUncertainty
Author: Manuel Marschall
Author-email: manuel.marschall@ptb.de
License: UNKNOWN
Platform: UNKNOWN
Classifier: Programming Language :: Python :: 3
Classifier: Operating System :: OS Independent
Requires-Python: >=3.6
